Metadata-Version: 2.1
Name: mobie
Version: 3.0.12
Summary: Viewer for big multi-modal image data
Home-page: https://github.com/mobie/mobie-viewer-fiji
Author: Christian Tischer
Author-email: christian.tischer@embl.de
Maintainer: Christian Tischer
Maintainer-email: christian.tischer@embl.de
License: UNKNOWN
Platform: UNKNOWN
Classifier: License :: OSI Approved :: BSD License
Classifier: Programming Language :: Python :: 3 :: Only
License-File: LICENSE.txt
